{
  "project_info": {
    "project_number": "627215924349",
    "firebase_url": "https://uidesign-5d353.firebaseio.com",
    "project_id": "uidesign-5d353",
    "storage_bucket": "uidesign-5d353.appspot.com"
  },
  "client": [
    {
      "client_info": {
        "mobilesdk_app_id": "1:627215924349:android:b551d5dd4442542ecb0514",
        "android_client_info": {
          "package_name": "com.example.firebasedictionary"
        }
      },
      "oauth_client": [
        {
          "client_id": "627215924349-ufgvdv2jb4d4k1496lmkau4vf3d33tfm.apps.googleusercontent.com",
          "client_type": 1,
          "android_info": {
            "package_name": "com.example.firebasedictionary",
            "certificate_hash": "3e9da734bc32e3c5087411e0eda7bd77c65dd940"
          }
        },
        {
          "client_id": "627215924349-ta62dtits5puqn2rg614d6h2d3nq7dkb.apps.googleusercontent.com",
          "client_type": 3
        }
      ],
      "api_key": [
        {
          "current_key": "AIzaSyDAck8SJS-1T2Svm69rd6OAE0pcfwj9d5U"
        }
      ],
      "services": {
        "appinvite_service": {
          "other_platform_oauth_client": [
            {
              "client_id": "627215924349-ta62dtits5puqn2rg614d6h2d3nq7dkb.apps.googleusercontent.com",
              "client_type": 3
            }
          ]
        }
      }
    },
    {
      "client_info": {
        "mobilesdk_app_id": "1:627215924349:android:da9ce103f1c19be3",
        "android_client_info": {
          "package_name": "com.example.uidesignlearn"
        }
      },
      "oauth_client": [
        {
          "client_id": "627215924349-i3cpk5la1rrpqkhhh4kj4sivmb7k4b9i.apps.googleusercontent.com",
          "client_type": 1,
          "android_info": {
            "package_name": "com.example.uidesignlearn",
            "certificate_hash": "3e9da734bc32e3c5087411e0eda7bd77c65dd940"
          }
        },
        {
          "client_id": "627215924349-ta62dtits5puqn2rg614d6h2d3nq7dkb.apps.googleusercontent.com",
          "client_type": 3
        }
      ],
      "api_key": [
        {
          "current_key": "AIzaSyDAck8SJS-1T2Svm69rd6OAE0pcfwj9d5U"
        }
      ],
      "services": {
        "appinvite_service": {
          "other_platform_oauth_client": [
            {
              "client_id": "627215924349-ta62dtits5puqn2rg614d6h2d3nq7dkb.apps.googleusercontent.com",
              "client_type": 3
            }
          ]
        }
      }
    }
  ],
  "configuration_version": "1"
}